cfn_guard_test/__init__.py
cfn_guard_test/case.py
cfn_guard_test/reader.py
cfn_guard_test/report.py
cfn_guard_test/rule.py
cfn_guard_test/runner.py
cfn_guard_test/suite.py
cfn_guard_test/suites.py
cfn_guard_test-0.8.3.dist-info/LICENSE.txt
cfn_guard_test-0.8.3.dist-info/METADATA
cfn_guard_test-0.8.3.dist-info/WHEEL
cfn_guard_test-0.8.3.dist-info/entry_points.txt
cfn_guard_test-0.8.3.dist-info/RECORD
